README.txt
bootstrap.py
buildout.cfg
setup.py
docs/HISTORY.txt
docs/LICENSE.GPL
docs/LICENSE.LGPL
docs/LICENSE.txt
src/chaoflow/__init__.py
src/chaoflow.testing.ipython.egg-info/PKG-INFO
src/chaoflow.testing.ipython.egg-info/SOURCES.txt
src/chaoflow.testing.ipython.egg-info/dependency_links.txt
src/chaoflow.testing.ipython.egg-info/entry_points.txt
src/chaoflow.testing.ipython.egg-info/namespace_packages.txt
src/chaoflow.testing.ipython.egg-info/not-zip-safe
src/chaoflow.testing.ipython.egg-info/requires.txt
src/chaoflow.testing.ipython.egg-info/top_level.txt
src/chaoflow/testing/__init__.py
src/chaoflow/testing/ipython/README.txt
src/chaoflow/testing/ipython/__init__.py
src/chaoflow/testing/ipython/tests.py