Metadata-Version: 1.0
Name: chaoflow.testing.ipython
Version: 0.2
Summary: User ipython interactively in your doctest
Home-page: http://github.com/chaoflow/chaoflow.testing.ipython
Author: Florian Friesdorf
Author-email: flo@chaoflow.net
License: LGPL
Platform: UNKNOWN
Classifier: Development Status :: 4 - Beta
Classifier: Intended Audience :: Developers
Classifier: License :: OSI Approved :: GNU Library or Lesser General Public License (LGPL)
Classifier: Natural Language :: English
Classifier: Operating System :: OS Independent
Classifier: Programming Language :: Python
Classifier: Topic :: Software Development :: Testing
